aiostreammagic/__init__.py
aiostreammagic/const.py
aiostreammagic/endpoints.py
aiostreammagic/exceptions.py
aiostreammagic/models.py
aiostreammagic/py.typed
aiostreammagic/stream_magic.py
aiostreammagic-2.11.0.dist-info/LICENSE
aiostreammagic-2.11.0.dist-info/METADATA
aiostreammagic-2.11.0.dist-info/WHEEL
aiostreammagic-2.11.0.dist-info/RECORD
