Metadata-Version: 2.3
Name: aiostreammagic
Version: 2.11.0
Summary: An async python package for interfacing with Cambridge Audio / Stream Magic compatible streamers.
License: MIT
Author: Noah Husby
Author-email: 32528627+noahhusby@users.noreply.github.com
Maintainer: Noah Husby
Maintainer-email: 32528627+noahhusby@users.noreply.github.com
Requires-Python: >=3.11,<4.0
Classifier: License :: OSI Approved :: MIT License
Classifier: Programming Language :: Python :: 3
Classifier: Programming Language :: Python :: 3.11
Classifier: Programming Language :: Python :: 3.12
Classifier: Programming Language :: Python :: 3.13
Requires-Dist: aiohttp (>=3.11.7,<4.0.0)
Requires-Dist: mashumaro (>=3.11,<4.0)
Requires-Dist: orjson (>=3.9.0)
Requires-Dist: yarl (>=1.6.0)
Project-URL: Documentation, https://github.com/noahhusby/aiostreammagic
Project-URL: Homepage, https://github.com/noahhusby/aiostreammagic
Project-URL: Repository, https://github.com/noahhusby/aiostreammagic
